Metadata-Version: 2.1
Name: ozzymod
Version: 1.0.0
Summary: This Python module is to make your code more readable and shorter.
Home-page: 
Author: Major Ozzy
License: MIT
Keywords: modification
Classifier: Development Status :: 5 - Production/Stable
Classifier: Intended Audience :: Education
Classifier: Operating System :: Microsoft :: Windows :: Windows 10
Classifier: License :: OSI Approved :: MIT License
Classifier: Programming Language :: Python :: 3
License-File: LICENSE.txt
